devkitx/__init__.py
devkitx/_version.py
devkitx/cli/__init__.py
devkitx/cli/main.py
devkitx/compliance/__init__.py
devkitx/compliance/audit_logger.py
devkitx/compliance/nist_controls.py
devkitx/compliance/pii_detector.py
devkitx/security/__init__.py
devkitx/security/crypto.py
devkitx/security/input_sanitizer.py
devkitx/security/secrets_scanner.py
devkitx/utils/__init__.py
devkitx/utils/json_utils.py
devkitx/utils/string_utils.py
devkitx/utils/time_utils.py
devkitx/utils/validation.py
devkitx-2.0.1.dist-info/METADATA
devkitx-2.0.1.dist-info/WHEEL
devkitx-2.0.1.dist-info/entry_points.txt
devkitx-2.0.1.dist-info/RECORD
