Metadata-Version: 2.4
Name: devkitx
Version: 2.0.1
Summary: Security-first Python utilities for government, healthcare, and financial applications.
Project-URL: Homepage, https://github.com/SerityOps/devkitx
Project-URL: Documentation, https://devkitx.readthedocs.io
Project-URL: Repository, https://github.com/SerityOps/devkitx
Project-URL: Issues, https://github.com/SerityOps/devkitx/issues
Author: LadyCami
License: MIT
Keywords: audit,compliance,fedramp,hipaa,nist,pii,secrets,security,soc2,utilities
Classifier: Development Status :: 5 - Production/Stable
Classifier: Intended Audience :: Developers
Classifier: License :: OSI Approved :: MIT License
Classifier: Programming Language :: Python :: 3
Classifier: Programming Language :: Python :: 3.10
Classifier: Programming Language :: Python :: 3.11
Classifier: Programming Language :: Python :: 3.12
Classifier: Topic :: Security
Classifier: Topic :: Software Development :: Libraries :: Python Modules
Classifier: Typing :: Typed
Requires-Python: >=3.10
Requires-Dist: asyncbridge>=1.0.0
Requires-Dist: configmerge>=1.0.0
Requires-Dist: httpx-defaults>=1.0.0
Provides-Extra: all
Requires-Dist: rich>=13.0.0; extra == 'all'
Requires-Dist: structlog>=23.0.0; extra == 'all'
Requires-Dist: typer>=0.9.0; extra == 'all'
Provides-Extra: audit
Requires-Dist: structlog>=23.0.0; extra == 'audit'
Provides-Extra: cli
Requires-Dist: rich>=13.0.0; extra == 'cli'
Requires-Dist: typer>=0.9.0; extra == 'cli'
Provides-Extra: dev
Requires-Dist: mypy>=1.0.0; extra == 'dev'
Requires-Dist: pytest-cov>=4.0.0; extra == 'dev'
Requires-Dist: pytest>=7.0.0; extra == 'dev'
Requires-Dist: rich>=13.0.0; extra == 'dev'
Requires-Dist: ruff>=0.1.0; extra == 'dev'
Requires-Dist: structlog>=23.0.0; extra == 'dev'
Requires-Dist: typer>=0.9.0; extra == 'dev'
